LICENSE
setup.py
telesco_utils/__init__.py
telesco_utils/datahub.py
telesco_utils/datahub_engine.py
telesco_utils/debug_info.py
telesco_utils/sql_helper.py
telesco_utils.egg-info/PKG-INFO
telesco_utils.egg-info/SOURCES.txt
telesco_utils.egg-info/dependency_links.txt
telesco_utils.egg-info/requires.txt
telesco_utils.egg-info/top_level.txt